repyter/__init__.py
repyter/report.py
repyter/template.html
repyter-0.1.0.dist-info/METADATA
repyter-0.1.0.dist-info/WHEEL
repyter-0.1.0.dist-info/licenses/LICENSE
repyter-0.1.0.dist-info/RECORD
