Metadata-Version: 2.4
Name: repyter
Version: 0.1.0
Summary: Report generator
License: MIT
License-File: LICENSE
Author: Cameron Grant
Author-email: 32722226+CameronJGrant@users.noreply.github.com
Requires-Python: >=3.13
Classifier: License :: OSI Approved :: MIT License
Classifier: Programming Language :: Python :: 3
Classifier: Programming Language :: Python :: 3.13
Classifier: Programming Language :: Python :: 3.14
Requires-Dist: jinja2 (>=3.1.6,<4.0.0)
Requires-Dist: pandas (>=2.3.1,<3.0.0)
